audio_bible_tools/__init__.py
audio_bible_tools/downloader.py
audio_bible_tools-0.1.5.dist-info/LICENSE
audio_bible_tools-0.1.5.dist-info/METADATA
audio_bible_tools-0.1.5.dist-info/WHEEL
audio_bible_tools-0.1.5.dist-info/top_level.txt
audio_bible_tools-0.1.5.dist-info/RECORD
