Metadata-Version: 2.1
Name: audio_bible_tools
Version: 0.1.5
Summary: Tools for use in building the audio-bible app
Home-page: https://audio-bible.github.io
Author: Brian Onang'o
Author-email: surgbc@gmail.com
Project-URL: Homepage, https://github.com/audio-bible/audio-bible-tools
Project-URL: Issues, https://github.com/audio-bible/audio-bible-tools/issues
Classifier: Programming Language :: Python :: 3
Classifier: License :: OSI Approved :: Apache Software License
Classifier: Operating System :: OS Independent
Requires-Python: >=3.8
License-File: LICENSE
Requires-Dist: yt-dlp
Requires-Dist: requests
